vue_helper/__init__.py
vue_helper/apps.py
vue_helper/context_processors.py
vue_helper/dist.py
vue_helper/exceptions.py
vue_helper/templates/vue_helper/vue_preload_scripts.html
vue_helper/templates/vue_helper/vue_preload_styles.html
vue_helper/templates/vue_helper/vue_scripts.html
vue_helper/templates/vue_helper/vue_styles.html
vue_helper/templatetags/__init__.py
vue_helper/templatetags/vue_helper_tags.py
vue_helper/tests/__init__.py
vue_helper/tests/test_utils.py
vue_helper/tests/test_views.py
vue_helper/utils.py
django_vue_helper-0.1.4.dist-info/LICENSE
django_vue_helper-0.1.4.dist-info/WHEEL
django_vue_helper-0.1.4.dist-info/METADATA
django_vue_helper-0.1.4.dist-info/RECORD
